LICENSE
README.md
setup.py
consultanit.egg-info/PKG-INFO
consultanit.egg-info/SOURCES.txt
consultanit.egg-info/dependency_links.txt
consultanit.egg-info/requires.txt
consultanit.egg-info/top_level.txt
consultanitbolivia/__init__.py
consultanitbolivia/verificar.py