Metadata-Version: 2.1
Name: consultanit
Version: 0.1
Summary: Este paquete le permite verificar el ESTADO ACTUAL DEL NIT, en caso de no existir retorna un mensaje indicando que no existe.
Home-page: https://github.com/zxvega/consulta-nit-bolivia
Author: Giovanni Vega
License: MIT
License-File: LICENSE
